color_text/PyQt5_util.py
color_text/PySide2_util.py
color_text/__init__.py
color_text/add_watermark.py
color_text/color.py
color_text/examples.py
color_text/functions.py
color_text/get_input.py
color_text/handles.py
color_text/output.py
color_text/doc/__init__.py
color_text-4.2.2.data/data/Lib/site-packages/color_text/ffmpeg.exe
color_text-4.2.2.data/data/Lib/site-packages/color_text/doc/help.doc
color_text-4.2.2.data/data/Lib/site-packages/color_text/doc/help.docx
color_text-4.2.2.data/data/Lib/site-packages/color_text/doc/help.md
color_text-4.2.2.data/data/Lib/site-packages/color_text/doc/help.mhtml
color_text-4.2.2.data/data/Lib/site-packages/color_text/doc/help.odt
color_text-4.2.2.data/data/Lib/site-packages/color_text/doc/help.pdf
color_text-4.2.2.data/data/Lib/site-packages/color_text/doc/help.rtf
color_text-4.2.2.data/data/Lib/site-packages/color_text/doc/help.xml
color_text-4.2.2.data/data/Lib/site-packages/color_text/doc/help.xps
color_text-4.2.2.data/scripts/color_text-examples.cmd
color_text-4.2.2.data/scripts/color_text-examples.ps1
color_text-4.2.2.data/scripts/color_text-examples.py
color_text-4.2.2.dist-info/LICENSE.txt
color_text-4.2.2.dist-info/METADATA
color_text-4.2.2.dist-info/WHEEL
color_text-4.2.2.dist-info/entry_points.txt
color_text-4.2.2.dist-info/top_level.txt
color_text-4.2.2.dist-info/RECORD
