Metadata-Version: 2.1
Name: color-text
Version: 4.2.2
Summary: A library for printing colored text, getting colored input, changing Qt5 controls' colors, adding watermarks to the video.   一个用来打印彩色文字、获取彩色的输入、更改Qt5控件的颜色、给视频添加水印的库。
Home-page: https://github.com/ChongChong-qyx/color-text
Author: A Chinese who likes programming   一个热爱编程的中国人
Author-email: colortextpackage@yandex.com
License: MIT
Keywords: color_text,color text,colour_text,colour text,彩色文字,有颜色的文字,颜色文字,彩色文本,有颜色的文本,颜色文本,color_words,color words,colour_words,colour words,color_word,color word,colour_word,colour word
Platform: Windows
Classifier: Intended Audience :: Developers
Classifier: Development Status :: 5 - Production/Stable
Classifier: Programming Language :: Python
Classifier: Programming Language :: Python :: Implementation :: CPython
Classifier: Programming Language :: Python :: 3.8
Classifier: Operating System :: Microsoft
Classifier: Operating System :: Microsoft :: Windows
Classifier: Operating System :: MacOS
Classifier: Operating System :: MacOS :: MacOS X
Classifier: Operating System :: POSIX
Classifier: Operating System :: POSIX :: Linux
Classifier: License :: OSI Approved
Classifier: License :: OSI Approved :: MIT License
Classifier: Environment :: Win32 (MS Windows)
Classifier: Natural Language :: English
Classifier: Topic :: Software Development
Classifier: Topic :: Software Development :: Libraries
Classifier: Topic :: Software Development :: Libraries :: Python Modules
Requires-Python: >=3.0, <4.0
